consistent_lineup_setup/__init__.py
consistent_lineup_setup/obtain_played_minutes.py
consistent_lineup_setup/obtainer.py
consistent_lineup_setup-0.1.0.dist-info/LICENSE
consistent_lineup_setup-0.1.0.dist-info/WHEEL
consistent_lineup_setup-0.1.0.dist-info/METADATA
consistent_lineup_setup-0.1.0.dist-info/RECORD
