Metadata-Version: 2.3
Name: consistent_lineup_setup
Version: 0.1.0
Summary: A module to obtain played minutes
Home-page: https://github.com/niesfutbol/consistent_lineup_setup
Author: NIES
Author-email: nepo@nies.futbol
Requires-Python: >=3.9
Classifier: License :: OSI Approved :: GNU General Public License v3 or later (GPLv3+)
Requires-Dist: pandas
